roi_device/__init__.py
roi_device/iot_device/__init__.py
roi_device/iot_device/iot_device.py
roi_device/iot_device/iot_device_info.py
roi_device/iot_device/iot_tools.py
roi_device/iot_thing/__init__.py
roi_device/iot_thing/iot_thing.py
roi_device/iot_thing/iot_thing_event.py
roi_device/iot_thing/iot_thing_properties.py
roi_device/iot_thing/iot_thing_service.py
roi_device/iot_thing/iot_thing_shadow.py
roi_device/iot_topic/__init__.py
roi_device/iot_topic/iot_thing_property_desired.py
roi_device/iot_topic/iot_thing_property_desired_clear.py
roi_device/iot_topic/iot_topic.py
roi_device/iot_topic/iot_topic_thing.py
roi_device-1.0.13.dist-info/LICENSE.txt
roi_device-1.0.13.dist-info/METADATA
roi_device-1.0.13.dist-info/WHEEL
roi_device-1.0.13.dist-info/top_level.txt
roi_device-1.0.13.dist-info/RECORD
