Metadata-Version: 2.1
Name: roi-device
Version: 1.0.13
Summary: roi iot device , support all iot cloud platform in future
Home-page: https://pypi.org/project/roi-device/
Author: labelnet
Author-email: labelnet@smartahc.com
License: MIT
Keywords: roi
Platform: UNKNOWN
Requires-Python: >=3.5
Requires-Dist: aliyun-iot-linkkit (==1.2.2)
Requires-Dist: pycryptodome (==3.7.2)
